knowledge_devourer/__init__.py
knowledge_devourer/cli.py
knowledge_devourer/core/__init__.py
knowledge_devourer/core/config.py
knowledge_devourer/core/downloader.py
knowledge_devourer/core/instagram_client.py
knowledge_devourer/core/processor.py
knowledge_devourer/core/utils.py
knowledge_devourer-1.0.5.dist-info/METADATA
knowledge_devourer-1.0.5.dist-info/WHEEL
knowledge_devourer-1.0.5.dist-info/entry_points.txt
knowledge_devourer-1.0.5.dist-info/top_level.txt
knowledge_devourer-1.0.5.dist-info/RECORD
